{
  "id": "radio_card",
  "name": "Radio Card",
  "description": "Composite export for RadioCard and RadioGroup.",
  "category": "form",
  "tags": [
    "form",
    "selection",
    "composite"
  ],
  "dependencies": {
    "shared": [],
    "components": [
      "radio_group"
    ],
    "pubspec": {}
  },
  "files": [
    "README.md",
    "meta.json",
    "radio_card.dart",
    "radio_card.meta.json"
  ],
  "api": {
    "constructors": [],
    "callbacks": [],
    "types": [
      "`RadioCard<T>`",
      "`RadioGroup<T>`",
      "`RadioGroupController<T>`",
      "`RadioItem<T>`"
    ]
  },
  "version": "1.0.0"
}
