{
  "$schema": "../../../../readme_meta.schema.json",
  "schemaVersion": 1,
  "id": "dropdown_menu",
  "name": "Dropdown Menu",
  "description": "Dropdown menu overlay built on menu primitives.",
  "install": "flutter_shadcn add dropdown_menu",
  "import": "import 'package:<your_app>/ui/shadcn/overlay/dropdown_menu/dropdown_menu.dart';",
  "whenToUse": {
    "use": [
      "you need a compact dropdown for a button or field.",
      "you want to reuse menu items and styling."
    ],
    "avoid": [
      "you need a full-screen sheet or dialog."
    ]
  },
  "examples": {
    "minimal": "DropdownMenu(\n  children: [\n    MenuButton(child: const Text('New'), onPressed: (context) {}),\n    MenuButton(child: const Text('Open'), onPressed: (context) {}),\n  ],\n)"
  },
  "patterns": [
    {
      "title": "Show as overlay",
      "code": "showDropdown(\n  context: context,\n  builder: (context) => DropdownMenu(\n    children: [\n      MenuButton(child: const Text('Rename'), onPressed: (context) {}),\n    ],\n  ),\n)"
    }
  ],
  "api": {
    "constructors": [],
    "callbacks": [],
    "widgets_and_helpers": [
      "`DropdownMenu`",
      "`showDropdown`",
      "`DropdownMenuTheme`"
    ]
  },
  "theming": [
    "`DropdownMenuTheme` controls surface blur and opacity."
  ],
  "accessibility": [
    "Ensure menu items are keyboard-focusable and labeled."
  ],
  "do": [
    "Keep menu groups short and clear."
  ],
  "dont": [
    "Use dropdowns for long or nested navigation trees."
  ],
  "related": [
    "menu",
    "popup"
  ],
  "registryRules": [
    "One public class per file",
    "Helpers under `_impl/`"
  ]
}
