{
  "id": "collapsible",
  "title": "Collapsible Theme",
  "description": "Independent sections that toggle their own visibility Theme tokens and editor schema.",
  "schemaVersion": 1,
  "since": "1.0.0",
  "migrations": {},
  "groups": [
    {
      "title": "Theme",
      "description": "Generated fields discovered from `layout/collapsible` theme classes.",
      "fields": [
        {
          "type": "object",
          "name": "crossAxisAlignment",
          "label": "Cross Axis Alignment",
          "description": "Generated from Dart type `CrossAxisAlignment?`.",
          "defaultValue": null,
          "required": false,
          "isAdvanced": false,
          "visibleIf": [],
          "validation": {
            "clamp": "reject"
          },
          "ui": {
            "control": "input"
          },
          "since": "1.0.0"
        },
        {
          "type": "object",
          "name": "iconCollapsed",
          "label": "Icon Collapsed",
          "description": "Generated from Dart type `IconData?`.",
          "defaultValue": null,
          "required": false,
          "isAdvanced": false,
          "visibleIf": [],
          "validation": {
            "clamp": "reject"
          },
          "ui": {
            "control": "input"
          },
          "since": "1.0.0"
        },
        {
          "type": "object",
          "name": "iconExpanded",
          "label": "Icon Expanded",
          "description": "Generated from Dart type `IconData?`.",
          "defaultValue": null,
          "required": false,
          "isAdvanced": false,
          "visibleIf": [],
          "validation": {
            "clamp": "reject"
          },
          "ui": {
            "control": "input"
          },
          "since": "1.0.0"
        },
        {
          "type": "number",
          "name": "iconGap",
          "label": "Icon Gap",
          "description": "Generated from Dart type `double?`.",
          "defaultValue": null,
          "required": false,
          "isAdvanced": false,
          "visibleIf": [],
          "validation": {
            "clamp": "reject"
          },
          "ui": {
            "control": "input"
          },
          "precision": 2,
          "since": "1.0.0"
        },
        {
          "type": "object",
          "name": "mainAxisAlignment",
          "label": "Main Axis Alignment",
          "description": "Generated from Dart type `MainAxisAlignment?`.",
          "defaultValue": null,
          "required": false,
          "isAdvanced": false,
          "visibleIf": [],
          "validation": {
            "clamp": "reject"
          },
          "ui": {
            "control": "input"
          },
          "since": "1.0.0"
        },
        {
          "type": "number",
          "name": "padding",
          "label": "Padding",
          "description": "Generated from Dart type `double?`.",
          "defaultValue": null,
          "required": false,
          "isAdvanced": false,
          "visibleIf": [],
          "validation": {
            "clamp": "reject"
          },
          "ui": {
            "control": "input"
          },
          "precision": 2,
          "since": "1.0.0"
        }
      ]
    }
  ],
  "$schema": "../../../component_theme.schema.json"
}
