{
  "$schema": "../manifests/themes.schema.json",
  "schemaVersion": 1,
  "generatedAt": "2026-02-20T02:59:20.595197Z",
  "id": "mono",
  "name": "Mono",
  "light": {
    "background": "0xFFFFFFFF",
    "foreground": "0xFF0A0A0A",
    "card": "0xFFFFFFFF",
    "cardForeground": "0xFF0A0A0A",
    "popover": "0xFFFFFFFF",
    "popoverForeground": "0xFF0A0A0A",
    "primary": "0xFF737373",
    "primaryForeground": "0xFFFAFAFA",
    "secondary": "0xFFF5F5F5",
    "secondaryForeground": "0xFF171717",
    "muted": "0xFFF5F5F5",
    "mutedForeground": "0xFF717171",
    "accent": "0xFFF5F5F5",
    "accentForeground": "0xFF171717",
    "destructive": "0xFFE7000B",
    "destructiveForeground": "0xFFF5F5F5",
    "border": "0xFFE5E5E5",
    "input": "0xFFE5E5E5",
    "ring": "0xFFA1A1A1",
    "chart1": "0xFF737373",
    "chart2": "0xFF737373",
    "chart3": "0xFF737373",
    "chart4": "0xFF737373",
    "chart5": "0xFF737373",
    "sidebar": "0xFFFAFAFA",
    "sidebarForeground": "0xFF0A0A0A",
    "sidebarPrimary": "0xFF171717",
    "sidebarPrimaryForeground": "0xFFFAFAFA",
    "sidebarAccent": "0xFFF5F5F5",
    "sidebarAccentForeground": "0xFF171717",
    "sidebarBorder": "0xFFE5E5E5",
    "sidebarRing": "0xFFA1A1A1"
  },
  "dark": {
    "background": "0xFF0A0A0A",
    "foreground": "0xFFFAFAFA",
    "card": "0xFF191919",
    "cardForeground": "0xFFFAFAFA",
    "popover": "0xFF262626",
    "popoverForeground": "0xFFFAFAFA",
    "primary": "0xFF737373",
    "primaryForeground": "0xFFFAFAFA",
    "secondary": "0xFF262626",
    "secondaryForeground": "0xFFFAFAFA",
    "muted": "0xFF262626",
    "mutedForeground": "0xFFA1A1A1",
    "accent": "0xFF404040",
    "accentForeground": "0xFFFAFAFA",
    "destructive": "0xFFFF6467",
    "destructiveForeground": "0xFF262626",
    "border": "0xFF383838",
    "input": "0xFF525252",
    "ring": "0xFF737373",
    "chart1": "0xFF737373",
    "chart2": "0xFF737373",
    "chart3": "0xFF737373",
    "chart4": "0xFF737373",
    "chart5": "0xFF737373",
    "sidebar": "0xFF171717",
    "sidebarForeground": "0xFFFAFAFA",
    "sidebarPrimary": "0xFFFAFAFA",
    "sidebarPrimaryForeground": "0xFF171717",
    "sidebarAccent": "0xFF262626",
    "sidebarAccentForeground": "0xFFFAFAFA",
    "sidebarBorder": "0xFFFFFFFF",
    "sidebarRing": "0xFF525252"
  },
  "tokens": {
    "light": {
      "radius": 0,
      "spacing": {
        "base": 3.84
      },
      "tracking": {
        "normal": 0
      },
      "shadows": {
        "shadow2xs": [
          {
            "x": 0,
            "y": 1,
            "blur": 0,
            "spread": 0,
            "color": "0x00000000"
          }
        ],
        "shadowXs": [
          {
            "x": 0,
            "y": 1,
            "blur": 0,
            "spread": 0,
            "color": "0x00000000"
          }
        ],
        "shadowSm": [
          {
            "x": 0,
            "y": 1,
            "blur": 0,
            "spread": 0,
            "color": "0x00000000"
          }
        ],
        "shadow": [
          {
            "x": 0,
            "y": 1,
            "blur": 0,
            "spread": 0,
            "color": "0x00000000"
          }
        ],
        "shadowMd": [
          {
            "x": 0,
            "y": 1,
            "blur": 0,
            "spread": 0,
            "color": "0x00000000"
          }
        ],
        "shadowLg": [
          {
            "x": 0,
            "y": 1,
            "blur": 0,
            "spread": 0,
            "color": "0x00000000"
          }
        ],
        "shadowXl": [
          {
            "x": 0,
            "y": 1,
            "blur": 0,
            "spread": 0,
            "color": "0x00000000"
          }
        ],
        "shadow2xl": [
          {
            "x": 0,
            "y": 1,
            "blur": 0,
            "spread": 0,
            "color": "0x00000000"
          }
        ]
      },
      "fontSans": "Geist Mono, monospace",
      "fontSerif": "Geist Mono, monospace",
      "fontMono": "Geist Mono, monospace"
    },
    "dark": {
      "radius": 0.5,
      "spacing": {
        "base": 3.84
      },
      "tracking": {
        "normal": 0
      },
      "shadows": {
        "shadow2xs": [
          {
            "x": 20.5,
            "y": 16.5,
            "blur": 25.5,
            "spread": -30,
            "color": "0x12000000"
          }
        ],
        "shadowXs": [
          {
            "x": 20.5,
            "y": 16.5,
            "blur": 25.5,
            "spread": -30,
            "color": "0x12000000"
          }
        ],
        "shadowSm": [
          {
            "x": 20.5,
            "y": 16.5,
            "blur": 25.5,
            "spread": -30,
            "color": "0x12000000"
          }
        ],
        "shadow": [
          {
            "x": 20.5,
            "y": 16.5,
            "blur": 25.5,
            "spread": -30,
            "color": "0x12000000"
          }
        ],
        "shadowMd": [
          {
            "x": 20.5,
            "y": 16.5,
            "blur": 25.5,
            "spread": -30,
            "color": "0x12000000"
          }
        ],
        "shadowLg": [
          {
            "x": 20.5,
            "y": 16.5,
            "blur": 25.5,
            "spread": -30,
            "color": "0x12000000"
          }
        ],
        "shadowXl": [
          {
            "x": 20.5,
            "y": 16.5,
            "blur": 25.5,
            "spread": -30,
            "color": "0x12000000"
          }
        ],
        "shadow2xl": [
          {
            "x": 20.5,
            "y": 16.5,
            "blur": 25.5,
            "spread": -30,
            "color": "0x12000000"
          }
        ]
      }
    }
  }
}