{
  "$schema": "../../../../manifests/readme_meta.schema.json",
  "schemaVersion": 1,
  "id": "file_input",
  "name": "File Input",
  "description": "Utilities for mapping file extensions to icon widgets.",
  "install": "flutter_shadcn add file_input",
  "import": "import 'package:<your_app>/ui/shadcn/form/file_input/file_input.dart';",
  "whenToUse": {
    "use": [
      "you need consistent file-type icons."
    ],
    "avoid": [
      "you already have a custom icon pipeline."
    ]
  },
  "examples": {
    "minimal": "FileIconProvider.builder(\n  builder: (ext) => const Icon(Icons.insert_drive_file),\n  child: Builder(\n    builder: (context) => FileIconProvider.buildIcon(context, 'pdf'),\n  ),\n)"
  },
  "patterns": [],
  "api": {
    "constructors": [
      "`FileIconProvider`",
      "`FileIconProvider.builder(builder: ..., child: ...)`",
      "`FileIconProvider(icons: ..., child: ...)`",
      "`FileIconBuilder` — `Widget Function(String extension)`"
    ],
    "callbacks": []
  },
  "theming": [
    "Icons inherit theme colors through `Icon` widgets."
  ],
  "accessibility": [
    "Provide semantic labels for file icons where appropriate."
  ],
  "do": [
    "Use a shared provider to keep file icons consistent."
  ],
  "dont": [
    "Hardcode icons per list item if a provider can be reused."
  ],
  "related": [
    "file_picker"
  ],
  "registryRules": [
    "One public class per file",
    "Helpers under `_impl/`"
  ]
}
