{
  "schemaVersion": 1,
  "id": "alert_dialog",
  "name": "AlertDialog",
  "description": "Modal alert dialog with customizable header, content, and actions.",
  "install": "flutter_shadcn add alert_dialog",
  "import": "import 'package:<your_app>/ui/shadcn/overlay/alert_dialog/alert_dialog.dart';",
  "whenToUse": {
    "use": [
      "you need a focused confirmation or alert surface.",
      "you want a styled modal without wiring overlays manually."
    ],
    "avoid": [
      "you need a full-screen dialog or custom route transitions."
    ]
  },
  "examples": {
    "minimal": "AlertDialog(\n  title: const Text('Delete file?'),\n  content: const Text('This action cannot be undone.'),\n  actions: [\n    TextButton(\n      onPressed: () => Navigator.of(context).pop(),\n      child: const Text('Cancel'),\n    ),\n    TextButton(\n      onPressed: _delete,\n      child: const Text('Delete'),\n    ),\n  ],\n)"
  },
  "patterns": [],
  "api": {
    "constructors": [
      "`AlertDialog`",
      "`leading`, `trailing`",
      "`title`, `content`, `actions`",
      "`surfaceBlur`, `surfaceOpacity`, `barrierColor`, `padding`"
    ],
    "callbacks": []
  },
  "theming": [
    "Uses `Theme.of(context)` surface tokens (radius, surface blur/opacity, colors)."
  ],
  "accessibility": [
    "Provide clear titles and actionable button labels."
  ],
  "do": [
    "Keep dialog content concise and scannable."
  ],
  "dont": [
    "Nest multiple modals or alerts."
  ],
  "related": [
    "dialog",
    "drawer"
  ],
  "registryRules": [
    "One public class per file",
    "Helpers under `_impl/`"
  ]
}
